discordbotdash/__init__.py
discordbotdash/dash.py
discordbotdash/app/__init__.py
discordbotdash/app/app.py
discordbotdash/app/static/css/bot.css
discordbotdash/app/static/css/button.css
discordbotdash/app/static/css/category.css
discordbotdash/app/static/css/commands.css
discordbotdash/app/static/css/console.css
discordbotdash/app/static/js/main.js
discordbotdash/app/templates/cogs.html
discordbotdash/app/templates/commands.html
discordbotdash/app/templates/console.html
discordbotdash/app/templates/shards.html
discordbotdash-1.2.3.dist-info/LICENSE
discordbotdash-1.2.3.dist-info/METADATA
discordbotdash-1.2.3.dist-info/WHEEL
discordbotdash-1.2.3.dist-info/top_level.txt
discordbotdash-1.2.3.dist-info/RECORD
