Metadata-Version: 2.1
Name: discordbotdash
Version: 1.2.3
Summary: A python package for testing/managing your discord.py bot in browser.
Home-page: https://github.com/xCloudzx/discordbotdash
Author: Sachin Raja
Author-email: sachinraja2349@gmail.com
License: MIT
Platform: UNKNOWN
Classifier: Programming Language :: Python :: 3
Classifier: License :: OSI Approved :: MIT License
Classifier: Operating System :: OS Independent
